logging_settings/__init__.py
logging_settings/formatters.py
logging_settings/models.py
logging_settings/settings.py
logging_settings/utils.py
logging_settings-0.1.15.dist-info/LICENSE
logging_settings-0.1.15.dist-info/METADATA
logging_settings-0.1.15.dist-info/WHEEL
logging_settings-0.1.15.dist-info/RECORD
