Metadata-Version: 2.3
Name: logging_settings
Version: 0.1.15
Summary: 
License: Apache-2.0
Author: Bakminstof
Author-email: bakminstof@yandex.ru
Requires-Python: >=3.12,<4.0
Classifier: License :: OSI Approved :: Apache Software License
Classifier: Programming Language :: Python :: 3
Classifier: Programming Language :: Python :: 3.12
Classifier: Programming Language :: Python :: 3.13
Provides-Extra: all
Provides-Extra: loki
Requires-Dist: colorama (>=0.4.6,<0.5.0)
Requires-Dist: pydantic (>=2.11.7,<3.0.0)
Requires-Dist: pydantic-settings (>=2.10.1,<3.0.0)
Requires-Dist: python-logging-loki (>=0.3.1,<0.4.0) ; extra == "loki"
